{"declaration":{"attributes":{"version":"1.0","encoding":"utf-8"}},"elements":[{"type":"comment","comment":"File created using MBINCompiler version (3.68.0)"},{"type":"element","name":"Data","attributes":{"template":"GcUnlockableTwitchRewards"},"elements":[{"type":"element","name":"Property","attributes":{"name":"Table"},"elements":[{"type":"element","name":"Property","attributes":{"value":"GcUnlockableTwitchReward.xml"},"elements":[{"type":"element","name":"Property","attributes":{"name":"TwitchId","value":"TWITCH_085"}},{"type":"element","name":"Property","attributes":{"name":"ProductId","value":"TWITCH_FIREW02E"}},{"type":"element","name":"Property","attributes":{"name":"LinkedGroupId","value":"TWITCH_FIREW01"}}]},{"type":"element","name":"Property","attributes":{"value":"GcUnlockableTwitchReward.xml"},"elements":[{"type":"element","name":"Property","attributes":{"name":"TwitchId","value":"TWITCH_084"}},{"type":"element","name":"Property","attributes":{"name":"ProductId","value":"TWITCH_FIREW02D"}},{"type":"element","name":"Property","attributes":{"name":"LinkedGroupId","value":"TWITCH_FIREW01"}}]},{"type":"element","name":"Property","attributes":{"value":"GcUnlockableTwitchReward.xml"},"elements":[{"type":"element","name":"Property","attributes":{"name":"TwitchId","value":"TWITCH_083"}},{"type":"element","name":"Property","attributes":{"name":"ProductId","value":"TWITCH_FIREW02C"}},{"type":"element","name":"Property","attributes":{"name":"LinkedGroupId","value":"TWITCH_FIREW01"}}]},{"type":"element","name":"Property","attributes":{"value":"GcUnlockableTwitchReward.xml"},"elements":[{"type":"element","name":"Property","attributes":{"name":"TwitchId","value":"TWITCH_082"}},{"type":"element","name":"Property","attributes":{"name":"ProductId","value":"TWITCH_FIREW02B"}},{"type":"element","name":"Property","attributes":{"name":"LinkedGroupId","value":"TWITCH_FIREW01"}}]},{"type":"element","name":"Property","attributes":{"value":"GcUnlockableTwitchReward.xml"},"elements":[{"type":"element","name":"Property","attributes":{"name":"TwitchId","value":"TWITCH_081"}},{"type":"element","name":"Property","attributes":{"name":"ProductId","value":"TWITCH_FIREW02A"}},{"type":"element","name":"Property","attributes":{"name":"LinkedGroupId","value":"TWITCH_FIREW01"}}]},{"type":"element","name":"Property","attributes":{"value":"GcUnlockableTwitchReward.xml"},"elements":[{"type":"element","name":"Property","attributes":{"name":"TwitchId","value":"TWITCH_080"}},{"type":"element","name":"Property","attributes":{"name":"ProductId","value":"SPEC_EXOTIC6"}},{"type":"element","name":"Property","attributes":{"name":"LinkedGroupId","value":""}}]},{"type":"element","name":"Property","attributes":{"value":"GcUnlockableTwitchReward.xml"},"elements":[{"type":"element","name":"Property","attributes":{"name":"TwitchId","value":"TWITCH_079"}},{"type":"element","name":"Property","attributes":{"name":"ProductId","value":"SPEC_EXOTIC5"}},{"type":"element","name":"Property","attributes":{"name":"LinkedGroupId","value":""}}]},{"type":"element","name":"Property","attributes":{"value":"GcUnlockableTwitchReward.xml"},"elements":[{"type":"element","name":"Property","attributes":{"name":"TwitchId","value":"TWITCH_078"}},{"type":"element","name":"Property","attributes":{"name":"ProductId","value":"SPEC_EXOTIC4"}},{"type":"element","name":"Property","attributes":{"name":"LinkedGroupId","value":""}}]},{"type":"element","name":"Property","attributes":{"value":"GcUnlockableTwitchReward.xml"},"elements":[{"type":"element","name":"Property","attributes":{"name":"TwitchId","value":"TWITCH_077"}},{"type":"element","name":"Property","attributes":{"name":"ProductId","value":"SPEC_EXOTIC3"}},{"type":"element","name":"Property","attributes":{"name":"LinkedGroupId","value":""}}]},{"type":"element","name":"Property","attributes":{"value":"GcUnlockableTwitchReward.xml"},"elements":[{"type":"element","name":"Property","attributes":{"name":"TwitchId","value":"TWITCH_076"}},{"type":"element","name":"Property","attributes":{"name":"ProductId","value":"SPEC_HELMET05"}},{"type":"element","name":"Property","attributes":{"name":"LinkedGroupId","value":""}}]},{"type":"element","name":"Property","attributes":{"value":"GcUnlockableTwitchReward.xml"},"elements":[{"type":"element","name":"Property","attributes":{"name":"TwitchId","value":"TWITCH_075"}},{"type":"element","name":"Property","attributes":{"name":"ProductId","value":"STATUE_ATLAS_S"}},{"type":"element","name":"Property","attributes":{"name":"LinkedGroupId","value":""}}]},{"type":"element","name":"Property","attributes":{"value":"GcUnlockableTwitchReward.xml"},"elements":[{"type":"element","name":"Property","attributes":{"name":"TwitchId","value":"TWITCH_074"}},{"type":"element","name":"Property","attributes":{"name":"ProductId","value":"BASE_TOYCUBE"}},{"type":"element","name":"Property","attributes":{"name":"LinkedGroupId","value":""}}]},{"type":"element","name":"Property","attributes":{"value":"GcUnlockableTwitchReward.xml"},"elements":[{"type":"element","name":"Property","attributes":{"name":"TwitchId","value":"TWITCH_073"}},{"type":"element","name":"Property","attributes":{"name":"ProductId","value":"STATUE_ASTRO_S"}},{"type":"element","name":"Property","attributes":{"name":"LinkedGroupId","value":""}}]},{"type":"element","name":"Property","attributes":{"value":"GcUnlockableTwitchReward.xml"},"elements":[{"type":"element","name":"Property","attributes":{"name":"TwitchId","value":"TWITCH_072"}},{"type":"element","name":"Property","attributes":{"name":"ProductId","value":"BASE_LAVA3"}},{"type":"element","name":"Property","attributes":{"name":"LinkedGroupId","value":""}}]},{"type":"element","name":"Property","attributes":{"value":"GcUnlockableTwitchReward.xml"},"elements":[{"type":"element","name":"Property","attributes":{"name":"TwitchId","value":"TWITCH_071"}},{"type":"element","name":"Property","attributes":{"name":"ProductId","value":"SPEC_PETCUST2"}},{"type":"element","name":"Property","attributes":{"name":"LinkedGroupId","value":""}}]},{"type":"element","name":"Property","attributes":{"value":"GcUnlockableTwitchReward.xml"},"elements":[{"type":"element","name":"Property","attributes":{"name":"TwitchId","value":"TWITCH_070"}},{"type":"element","name":"Property","attributes":{"name":"ProductId","value":"SPEC_DECAL05"}},{"type":"element","name":"Property","attributes":{"name":"LinkedGroupId","value":""}}]},{"type":"element","name":"Property","attributes":{"value":"GcUnlockableTwitchReward.xml"},"elements":[{"type":"element","name":"Property","attributes":{"name":"TwitchId","value":"TWITCH_069"}},{"type":"element","name":"Property","attributes":{"name":"ProductId","value":"SPEC_DECAL04"}},{"type":"element","name":"Property","attributes":{"name":"LinkedGroupId","value":""}}]},{"type":"element","name":"Property","attributes":{"value":"GcUnlockableTwitchReward.xml"},"elements":[{"type":"element","name":"Property","attributes":{"name":"TwitchId","value":"TWITCH_068"}},{"type":"element","name":"Property","attributes":{"name":"ProductId","value":"SPEC_DECAL03"}},{"type":"element","name":"Property","attributes":{"name":"LinkedGroupId","value":""}}]},{"type":"element","name":"Property","attributes":{"value":"GcUnlockableTwitchReward.xml"},"elements":[{"type":"element","name":"Property","attributes":{"name":"TwitchId","value":"TWITCH_067"}},{"type":"element","name":"Property","attributes":{"name":"ProductId","value":"SPEC_DECAL01"}},{"type":"element","name":"Property","attributes":{"name":"LinkedGroupId","value":""}}]},{"type":"element","name":"Property","attributes":{"value":"GcUnlockableTwitchReward.xml"},"elements":[{"type":"element","name":"Property","attributes":{"name":"TwitchId","value":"TWITCH_066"}},{"type":"element","name":"Property","attributes":{"name":"ProductId","value":"SPEC_DECAL06"}},{"type":"element","name":"Property","attributes":{"name":"LinkedGroupId","value":""}}]},{"type":"element","name":"Property","attributes":{"value":"GcUnlockableTwitchReward.xml"},"elements":[{"type":"element","name":"Property","attributes":{"name":"TwitchId","value":"TWITCH_065"}},{"type":"element","name":"Property","attributes":{"name":"ProductId","value":"JETS_GREEN"}},{"type":"element","name":"Property","attributes":{"name":"LinkedGroupId","value":""}}]},{"type":"element","name":"Property","attributes":{"value":"GcUnlockableTwitchReward.xml"},"elements":[{"type":"element","name":"Property","attributes":{"name":"TwitchId","value":"TWITCH_064"}},{"type":"element","name":"Property","attributes":{"name":"ProductId","value":"JETS_RED"}},{"type":"element","name":"Property","attributes":{"name":"LinkedGroupId","value":""}}]},{"type":"element","name":"Property","attributes":{"value":"GcUnlockableTwitchReward.xml"},"elements":[{"type":"element","name":"Property","attributes":{"name":"TwitchId","value":"TWITCH_063"}},{"type":"element","name":"Property","attributes":{"name":"ProductId","value":"SHIP_RAINBOW"}},{"type":"element","name":"Property","attributes":{"name":"LinkedGroupId","value":""}}]},{"type":"element","name":"Property","attributes":{"value":"GcUnlockableTwitchReward.xml"},"elements":[{"type":"element","name":"Property","attributes":{"name":"TwitchId","value":"TWITCH_062"}},{"type":"element","name":"Property","attributes":{"name":"ProductId","value":"SHIP_DARK"}},{"type":"element","name":"Property","attributes":{"name":"LinkedGroupId","value":""}}]},{"type":"element","name":"Property","attributes":{"value":"GcUnlockableTwitchReward.xml"},"elements":[{"type":"element","name":"Property","attributes":{"name":"TwitchId","value":"TWITCH_061"}},{"type":"element","name":"Property","attributes":{"name":"ProductId","value":"JETS_BLUE"}},{"type":"element","name":"Property","attributes":{"name":"LinkedGroupId","value":""}}]},{"type":"element","name":"Property","attributes":{"value":"GcUnlockableTwitchReward.xml"},"elements":[{"type":"element","name":"Property","attributes":{"name":"TwitchId","value":"TWITCH_060"}},{"type":"element","name":"Property","attributes":{"name":"ProductId","value":"DECAL_HAZARD"}},{"type":"element","name":"Property","attributes":{"name":"LinkedGroupId","value":""}}]},{"type":"element","name":"Property","attributes":{"value":"GcUnlockableTwitchReward.xml"},"elements":[{"type":"element","name":"Property","attributes":{"name":"TwitchId","value":"TWITCH_059"}},{"type":"element","name":"Property","attributes":{"name":"ProductId","value":"BOBBLE_NULL"}},{"type":"element","name":"Property","attributes":{"name":"LinkedGroupId","value":""}}]},{"type":"element","name":"Property","attributes":{"value":"GcUnlockableTwitchReward.xml"},"elements":[{"type":"element","name":"Property","attributes":{"name":"TwitchId","value":"TWITCH_058"}},{"type":"element","name":"Property","attributes":{"name":"ProductId","value":"SPEC_EMOTE10"}},{"type":"element","name":"Property","attributes":{"name":"LinkedGroupId","value":""}}]},{"type":"element","name":"Property","attributes":{"value":"GcUnlockableTwitchReward.xml"},"elements":[{"type":"element","name":"Property","attributes":{"name":"TwitchId","value":"TWITCH_057"}},{"type":"element","name":"Property","attributes":{"name":"ProductId","value":"SPEC_EMOTE08"}},{"type":"element","name":"Property","attributes":{"name":"LinkedGroupId","value":""}}]},{"type":"element","name":"Property","attributes":{"value":"GcUnlockableTwitchReward.xml"},"elements":[{"type":"element","name":"Property","attributes":{"name":"TwitchId","value":"TWITCH_056"}},{"type":"element","name":"Property","attributes":{"name":"ProductId","value":"SPEC_EMOTE03"}},{"type":"element","name":"Property","attributes":{"name":"LinkedGroupId","value":""}}]},{"type":"element","name":"Property","attributes":{"value":"GcUnlockableTwitchReward.xml"},"elements":[{"type":"element","name":"Property","attributes":{"name":"TwitchId","value":"TWITCH_051"}},{"type":"element","name":"Property","attributes":{"name":"ProductId","value":"TWITCH_PET01"}},{"type":"element","name":"Property","attributes":{"name":"LinkedGroupId","value":""}}]},{"type":"element","name":"Property","attributes":{"value":"GcUnlockableTwitchReward.xml"},"elements":[{"type":"element","name":"Property","attributes":{"name":"TwitchId","value":"TWITCH_052"}},{"type":"element","name":"Property","attributes":{"name":"ProductId","value":"TWITCH_PET02"}},{"type":"element","name":"Property","attributes":{"name":"LinkedGroupId","value":""}}]},{"type":"element","name":"Property","attributes":{"value":"GcUnlockableTwitchReward.xml"},"elements":[{"type":"element","name":"Property","attributes":{"name":"TwitchId","value":"TWITCH_053"}},{"type":"element","name":"Property","attributes":{"name":"ProductId","value":"TWITCH_PET03"}},{"type":"element","name":"Property","attributes":{"name":"LinkedGroupId","value":""}}]},{"type":"element","name":"Property","attributes":{"value":"GcUnlockableTwitchReward.xml"},"elements":[{"type":"element","name":"Property","attributes":{"name":"TwitchId","value":"TWITCH_054"}},{"type":"element","name":"Property","attributes":{"name":"ProductId","value":"TWITCH_PET04"}},{"type":"element","name":"Property","attributes":{"name":"LinkedGroupId","value":""}}]},{"type":"element","name":"Property","attributes":{"value":"GcUnlockableTwitchReward.xml"},"elements":[{"type":"element","name":"Property","attributes":{"name":"TwitchId","value":"TWITCH_055"}},{"type":"element","name":"Property","attributes":{"name":"ProductId","value":"TWITCH_PET05"}},{"type":"element","name":"Property","attributes":{"name":"LinkedGroupId","value":""}}]},{"type":"element","name":"Property","attributes":{"value":"GcUnlockableTwitchReward.xml"},"elements":[{"type":"element","name":"Property","attributes":{"name":"TwitchId","value":"TWITCH_046"}},{"type":"element","name":"Property","attributes":{"name":"ProductId","value":"TWITCH_SHIP06"}},{"type":"element","name":"Property","attributes":{"name":"LinkedGroupId","value":""}}]},{"type":"element","name":"Property","attributes":{"value":"GcUnlockableTwitchReward.xml"},"elements":[{"type":"element","name":"Property","attributes":{"name":"TwitchId","value":"TWITCH_047"}},{"type":"element","name":"Property","attributes":{"name":"ProductId","value":"TWITCH_SHIP07"}},{"type":"element","name":"Property","attributes":{"name":"LinkedGroupId","value":""}}]},{"type":"element","name":"Property","attributes":{"value":"GcUnlockableTwitchReward.xml"},"elements":[{"type":"element","name":"Property","attributes":{"name":"TwitchId","value":"TWITCH_048"}},{"type":"element","name":"Property","attributes":{"name":"ProductId","value":"TWITCH_SHIP08B"}},{"type":"element","name":"Property","attributes":{"name":"LinkedGroupId","value":""}}]},{"type":"element","name":"Property","attributes":{"value":"GcUnlockableTwitchReward.xml"},"elements":[{"type":"element","name":"Property","attributes":{"name":"TwitchId","value":"TWITCH_049"}},{"type":"element","name":"Property","attributes":{"name":"ProductId","value":"TWITCH_SHIP09"}},{"type":"element","name":"Property","attributes":{"name":"LinkedGroupId","value":""}}]},{"type":"element","name":"Property","attributes":{"value":"GcUnlockableTwitchReward.xml"},"elements":[{"type":"element","name":"Property","attributes":{"name":"TwitchId","value":"TWITCH_050"}},{"type":"element","name":"Property","attributes":{"name":"ProductId","value":"TWITCH_SHIP10"}},{"type":"element","name":"Property","attributes":{"name":"LinkedGroupId","value":""}}]},{"type":"element","name":"Property","attributes":{"value":"GcUnlockableTwitchReward.xml"},"elements":[{"type":"element","name":"Property","attributes":{"name":"TwitchId","value":"TWITCH_038"}},{"type":"element","name":"Property","attributes":{"name":"ProductId","value":"SPEC_EXOTIC2"}},{"type":"element","name":"Property","attributes":{"name":"LinkedGroupId","value":""}}]},{"type":"element","name":"Property","attributes":{"value":"GcUnlockableTwitchReward.xml"},"elements":[{"type":"element","name":"Property","attributes":{"name":"TwitchId","value":"TWITCH_037"}},{"type":"element","name":"Property","attributes":{"name":"ProductId","value":"SPEC_EXOTIC1"}},{"type":"element","name":"Property","attributes":{"name":"LinkedGroupId","value":""}}]},{"type":"element","name":"Property","attributes":{"value":"GcUnlockableTwitchReward.xml"},"elements":[{"type":"element","name":"Property","attributes":{"name":"TwitchId","value":"TWITCH_035"}},{"type":"element","name":"Property","attributes":{"name":"ProductId","value":"SPEC_HELMET02"}},{"type":"element","name":"Property","attributes":{"name":"LinkedGroupId","value":""}}]},{"type":"element","name":"Property","attributes":{"value":"GcUnlockableTwitchReward.xml"},"elements":[{"type":"element","name":"Property","attributes":{"name":"TwitchId","value":"TWITCH_036"}},{"type":"element","name":"Property","attributes":{"name":"ProductId","value":"SPEC_HELMET03"}},{"type":"element","name":"Property","attributes":{"name":"LinkedGroupId","value":""}}]},{"type":"element","name":"Property","attributes":{"value":"GcUnlockableTwitchReward.xml"},"elements":[{"type":"element","name":"Property","attributes":{"name":"TwitchId","value":"TWITCH_034"}},{"type":"element","name":"Property","attributes":{"name":"ProductId","value":"BOBBLE_ATLAS"}},{"type":"element","name":"Property","attributes":{"name":"LinkedGroupId","value":""}}]},{"type":"element","name":"Property","attributes":{"value":"GcUnlockableTwitchReward.xml"},"elements":[{"type":"element","name":"Property","attributes":{"name":"TwitchId","value":"TWITCH_033"}},{"type":"element","name":"Property","attributes":{"name":"ProductId","value":"BOBBLE_NADA"}},{"type":"element","name":"Property","attributes":{"name":"LinkedGroupId","value":""}}]},{"type":"element","name":"Property","attributes":{"value":"GcUnlockableTwitchReward.xml"},"elements":[{"type":"element","name":"Property","attributes":{"name":"TwitchId","value":"TWITCH_032"}},{"type":"element","name":"Property","attributes":{"name":"ProductId","value":"BOBBLE_POLO"}},{"type":"element","name":"Property","attributes":{"name":"LinkedGroupId","value":""}}]},{"type":"element","name":"Property","attributes":{"value":"GcUnlockableTwitchReward.xml"},"elements":[{"type":"element","name":"Property","attributes":{"name":"TwitchId","value":"TWITCH_031"}},{"type":"element","name":"Property","attributes":{"name":"ProductId","value":"BOBBLE_ART"}},{"type":"element","name":"Property","attributes":{"name":"LinkedGroupId","value":""}}]},{"type":"element","name":"Property","attributes":{"value":"GcUnlockableTwitchReward.xml"},"elements":[{"type":"element","name":"Property","attributes":{"name":"TwitchId","value":"TWITCH_030"}},{"type":"element","name":"Property","attributes":{"name":"ProductId","value":"BASE_AQUARIUM"}},{"type":"element","name":"Property","attributes":{"name":"LinkedGroupId","value":""}}]},{"type":"element","name":"Property","attributes":{"value":"GcUnlockableTwitchReward.xml"},"elements":[{"type":"element","name":"Property","attributes":{"name":"TwitchId","value":"TWITCH_029"}},{"type":"element","name":"Property","attributes":{"name":"ProductId","value":"BASE_ROBOTOY"}},{"type":"element","name":"Property","attributes":{"name":"LinkedGroupId","value":""}}]},{"type":"element","name":"Property","attributes":{"value":"GcUnlockableTwitchReward.xml"},"elements":[{"type":"element","name":"Property","attributes":{"name":"TwitchId","value":"TWITCH_028"}},{"type":"element","name":"Property","attributes":{"name":"ProductId","value":"BASE_TERRARIUM"}},{"type":"element","name":"Property","attributes":{"name":"LinkedGroupId","value":""}}]},{"type":"element","name":"Property","attributes":{"value":"GcUnlockableTwitchReward.xml"},"elements":[{"type":"element","name":"Property","attributes":{"name":"TwitchId","value":"TWITCH_027"}},{"type":"element","name":"Property","attributes":{"name":"ProductId","value":"STATUE_ASTRO_G"}},{"type":"element","name":"Property","attributes":{"name":"LinkedGroupId","value":""}}]},{"type":"element","name":"Property","attributes":{"value":"GcUnlockableTwitchReward.xml"},"elements":[{"type":"element","name":"Property","attributes":{"name":"TwitchId","value":"TWITCH_009"}},{"type":"element","name":"Property","attributes":{"name":"ProductId","value":"JETS_RAINBOW"}},{"type":"element","name":"Property","attributes":{"name":"LinkedGroupId","value":""}}]},{"type":"element","name":"Property","attributes":{"value":"GcUnlockableTwitchReward.xml"},"elements":[{"type":"element","name":"Property","attributes":{"name":"TwitchId","value":"TWITCH_001"}},{"type":"element","name":"Property","attributes":{"name":"ProductId","value":"TWITCH_FIREW01A"}},{"type":"element","name":"Property","attributes":{"name":"LinkedGroupId","value":"TWITCH_FIREW01"}}]},{"type":"element","name":"Property","attributes":{"value":"GcUnlockableTwitchReward.xml"},"elements":[{"type":"element","name":"Property","attributes":{"name":"TwitchId","value":"TWITCH_002"}},{"type":"element","name":"Property","attributes":{"name":"ProductId","value":"TWITCH_FIREW01B"}},{"type":"element","name":"Property","attributes":{"name":"LinkedGroupId","value":"TWITCH_FIREW01"}}]},{"type":"element","name":"Property","attributes":{"value":"GcUnlockableTwitchReward.xml"},"elements":[{"type":"element","name":"Property","attributes":{"name":"TwitchId","value":"TWITCH_003"}},{"type":"element","name":"Property","attributes":{"name":"ProductId","value":"TWITCH_FIREW01C"}},{"type":"element","name":"Property","attributes":{"name":"LinkedGroupId","value":"TWITCH_FIREW01"}}]},{"type":"element","name":"Property","attributes":{"value":"GcUnlockableTwitchReward.xml"},"elements":[{"type":"element","name":"Property","attributes":{"name":"TwitchId","value":"TWITCH_044"}},{"type":"element","name":"Property","attributes":{"name":"ProductId","value":"TWITCH_FIREW01D"}},{"type":"element","name":"Property","attributes":{"name":"LinkedGroupId","value":"TWITCH_FIREW01"}}]},{"type":"element","name":"Property","attributes":{"value":"GcUnlockableTwitchReward.xml"},"elements":[{"type":"element","name":"Property","attributes":{"name":"TwitchId","value":"TWITCH_045"}},{"type":"element","name":"Property","attributes":{"name":"ProductId","value":"TWITCH_FIREW01E"}},{"type":"element","name":"Property","attributes":{"name":"LinkedGroupId","value":"TWITCH_FIREW01"}}]},{"type":"element","name":"Property","attributes":{"value":"GcUnlockableTwitchReward.xml"},"elements":[{"type":"element","name":"Property","attributes":{"name":"TwitchId","value":"TWITCH_039"}},{"type":"element","name":"Property","attributes":{"name":"ProductId","value":"TWITCH_GUNUP01A"}},{"type":"element","name":"Property","attributes":{"name":"LinkedGroupId","value":"TWITCH_GUNUP01"}}]},{"type":"element","name":"Property","attributes":{"value":"GcUnlockableTwitchReward.xml"},"elements":[{"type":"element","name":"Property","attributes":{"name":"TwitchId","value":"TWITCH_040"}},{"type":"element","name":"Property","attributes":{"name":"ProductId","value":"TWITCH_GUNUP01B"}},{"type":"element","name":"Property","attributes":{"name":"LinkedGroupId","value":"TWITCH_GUNUP01"}}]},{"type":"element","name":"Property","attributes":{"value":"GcUnlockableTwitchReward.xml"},"elements":[{"type":"element","name":"Property","attributes":{"name":"TwitchId","value":"TWITCH_041"}},{"type":"element","name":"Property","attributes":{"name":"ProductId","value":"TWITCH_GUNUP01C"}},{"type":"element","name":"Property","attributes":{"name":"LinkedGroupId","value":"TWITCH_GUNUP01"}}]},{"type":"element","name":"Property","attributes":{"value":"GcUnlockableTwitchReward.xml"},"elements":[{"type":"element","name":"Property","attributes":{"name":"TwitchId","value":"TWITCH_042"}},{"type":"element","name":"Property","attributes":{"name":"ProductId","value":"TWITCH_GUNUP01D"}},{"type":"element","name":"Property","attributes":{"name":"LinkedGroupId","value":"TWITCH_GUNUP01"}}]},{"type":"element","name":"Property","attributes":{"value":"GcUnlockableTwitchReward.xml"},"elements":[{"type":"element","name":"Property","attributes":{"name":"TwitchId","value":"TWITCH_043"}},{"type":"element","name":"Property","attributes":{"name":"ProductId","value":"TWITCH_GUNUP01E"}},{"type":"element","name":"Property","attributes":{"name":"LinkedGroupId","value":"TWITCH_GUNUP01"}}]},{"type":"element","name":"Property","attributes":{"value":"GcUnlockableTwitchReward.xml"},"elements":[{"type":"element","name":"Property","attributes":{"name":"TwitchId","value":"TWITCH_014"}},{"type":"element","name":"Property","attributes":{"name":"ProductId","value":"SPEC_PETCUST1"}},{"type":"element","name":"Property","attributes":{"name":"LinkedGroupId","value":""}}]},{"type":"element","name":"Property","attributes":{"value":"GcUnlockableTwitchReward.xml"},"elements":[{"type":"element","name":"Property","attributes":{"name":"TwitchId","value":"TWITCH_004"}},{"type":"element","name":"Property","attributes":{"name":"ProductId","value":"SPEC_EMOTE01"}},{"type":"element","name":"Property","attributes":{"name":"LinkedGroupId","value":""}}]},{"type":"element","name":"Property","attributes":{"value":"GcUnlockableTwitchReward.xml"},"elements":[{"type":"element","name":"Property","attributes":{"name":"TwitchId","value":"TWITCH_005"}},{"type":"element","name":"Property","attributes":{"name":"ProductId","value":"SPEC_EMOTE02"}},{"type":"element","name":"Property","attributes":{"name":"LinkedGroupId","value":""}}]},{"type":"element","name":"Property","attributes":{"value":"GcUnlockableTwitchReward.xml"},"elements":[{"type":"element","name":"Property","attributes":{"name":"TwitchId","value":"TWITCH_007"}},{"type":"element","name":"Property","attributes":{"name":"ProductId","value":"SPEC_EMOTE04"}},{"type":"element","name":"Property","attributes":{"name":"LinkedGroupId","value":""}}]},{"type":"element","name":"Property","attributes":{"value":"GcUnlockableTwitchReward.xml"},"elements":[{"type":"element","name":"Property","attributes":{"name":"TwitchId","value":"TWITCH_008"}},{"type":"element","name":"Property","attributes":{"name":"ProductId","value":"SPEC_EMOTE05"}},{"type":"element","name":"Property","attributes":{"name":"LinkedGroupId","value":""}}]},{"type":"element","name":"Property","attributes":{"value":"GcUnlockableTwitchReward.xml"},"elements":[{"type":"element","name":"Property","attributes":{"name":"TwitchId","value":"TWITCH_006"}},{"type":"element","name":"Property","attributes":{"name":"ProductId","value":"SPEC_EMOTE09"}},{"type":"element","name":"Property","attributes":{"name":"LinkedGroupId","value":""}}]},{"type":"element","name":"Property","attributes":{"value":"GcUnlockableTwitchReward.xml"},"elements":[{"type":"element","name":"Property","attributes":{"name":"TwitchId","value":"TWITCH_010"}},{"type":"element","name":"Property","attributes":{"name":"ProductId","value":"SHIP_GOLD"}},{"type":"element","name":"Property","attributes":{"name":"LinkedGroupId","value":""}}]},{"type":"element","name":"Property","attributes":{"value":"GcUnlockableTwitchReward.xml"},"elements":[{"type":"element","name":"Property","attributes":{"name":"TwitchId","value":"TWITCH_012"}},{"type":"element","name":"Property","attributes":{"name":"ProductId","value":"SHIP_RED"}},{"type":"element","name":"Property","attributes":{"name":"LinkedGroupId","value":""}}]},{"type":"element","name":"Property","attributes":{"value":"GcUnlockableTwitchReward.xml"},"elements":[{"type":"element","name":"Property","attributes":{"name":"TwitchId","value":"TWITCH_013"}},{"type":"element","name":"Property","attributes":{"name":"ProductId","value":"SHIP_GREEN"}},{"type":"element","name":"Property","attributes":{"name":"LinkedGroupId","value":""}}]},{"type":"element","name":"Property","attributes":{"value":"GcUnlockableTwitchReward.xml"},"elements":[{"type":"element","name":"Property","attributes":{"name":"TwitchId","value":"TWITCH_011"}},{"type":"element","name":"Property","attributes":{"name":"ProductId","value":"JETS_DARK"}},{"type":"element","name":"Property","attributes":{"name":"LinkedGroupId","value":""}}]},{"type":"element","name":"Property","attributes":{"value":"GcUnlockableTwitchReward.xml"},"elements":[{"type":"element","name":"Property","attributes":{"name":"TwitchId","value":"TWITCH_015"}},{"type":"element","name":"Property","attributes":{"name":"ProductId","value":"BOBBLE_APOLLO"}},{"type":"element","name":"Property","attributes":{"name":"LinkedGroupId","value":""}}]},{"type":"element","name":"Property","attributes":{"value":"GcUnlockableTwitchReward.xml"},"elements":[{"type":"element","name":"Property","attributes":{"name":"TwitchId","value":"TWITCH_016"}},{"type":"element","name":"Property","attributes":{"name":"ProductId","value":"SPEC_HELMET01"}},{"type":"element","name":"Property","attributes":{"name":"LinkedGroupId","value":""}}]},{"type":"element","name":"Property","attributes":{"value":"GcUnlockableTwitchReward.xml"},"elements":[{"type":"element","name":"Property","attributes":{"name":"TwitchId","value":"TWITCH_017"}},{"type":"element","name":"Property","attributes":{"name":"ProductId","value":"TWITCH_SHIP01"}},{"type":"element","name":"Property","attributes":{"name":"LinkedGroupId","value":""}}]},{"type":"element","name":"Property","attributes":{"value":"GcUnlockableTwitchReward.xml"},"elements":[{"type":"element","name":"Property","attributes":{"name":"TwitchId","value":"TWITCH_019"}},{"type":"element","name":"Property","attributes":{"name":"ProductId","value":"TWITCH_SHIP02"}},{"type":"element","name":"Property","attributes":{"name":"LinkedGroupId","value":""}}]},{"type":"element","name":"Property","attributes":{"value":"GcUnlockableTwitchReward.xml"},"elements":[{"type":"element","name":"Property","attributes":{"name":"TwitchId","value":"TWITCH_020"}},{"type":"element","name":"Property","attributes":{"name":"ProductId","value":"TWITCH_SHIP03"}},{"type":"element","name":"Property","attributes":{"name":"LinkedGroupId","value":""}}]},{"type":"element","name":"Property","attributes":{"value":"GcUnlockableTwitchReward.xml"},"elements":[{"type":"element","name":"Property","attributes":{"name":"TwitchId","value":"TWITCH_021"}},{"type":"element","name":"Property","attributes":{"name":"ProductId","value":"TWITCH_SHIP04"}},{"type":"element","name":"Property","attributes":{"name":"LinkedGroupId","value":""}}]},{"type":"element","name":"Property","attributes":{"value":"GcUnlockableTwitchReward.xml"},"elements":[{"type":"element","name":"Property","attributes":{"name":"TwitchId","value":"TWITCH_022"}},{"type":"element","name":"Property","attributes":{"name":"ProductId","value":"TWITCH_SHIP05"}},{"type":"element","name":"Property","attributes":{"name":"LinkedGroupId","value":""}}]},{"type":"element","name":"Property","attributes":{"value":"GcUnlockableTwitchReward.xml"},"elements":[{"type":"element","name":"Property","attributes":{"name":"TwitchId","value":"TWITCH_018"}},{"type":"element","name":"Property","attributes":{"name":"ProductId","value":"TWITCH_GUN01"}},{"type":"element","name":"Property","attributes":{"name":"LinkedGroupId","value":""}}]},{"type":"element","name":"Property","attributes":{"value":"GcUnlockableTwitchReward.xml"},"elements":[{"type":"element","name":"Property","attributes":{"name":"TwitchId","value":"TWITCH_023"}},{"type":"element","name":"Property","attributes":{"name":"ProductId","value":"TWITCH_GUN02"}},{"type":"element","name":"Property","attributes":{"name":"LinkedGroupId","value":""}}]},{"type":"element","name":"Property","attributes":{"value":"GcUnlockableTwitchReward.xml"},"elements":[{"type":"element","name":"Property","attributes":{"name":"TwitchId","value":"TWITCH_024"}},{"type":"element","name":"Property","attributes":{"name":"ProductId","value":"TWITCH_GUN03"}},{"type":"element","name":"Property","attributes":{"name":"LinkedGroupId","value":""}}]},{"type":"element","name":"Property","attributes":{"value":"GcUnlockableTwitchReward.xml"},"elements":[{"type":"element","name":"Property","attributes":{"name":"TwitchId","value":"TWITCH_025"}},{"type":"element","name":"Property","attributes":{"name":"ProductId","value":"TWITCH_GUN04"}},{"type":"element","name":"Property","attributes":{"name":"LinkedGroupId","value":""}}]},{"type":"element","name":"Property","attributes":{"value":"GcUnlockableTwitchReward.xml"},"elements":[{"type":"element","name":"Property","attributes":{"name":"TwitchId","value":"TWITCH_026"}},{"type":"element","name":"Property","attributes":{"name":"ProductId","value":"TWITCH_GUN05"}},{"type":"element","name":"Property","attributes":{"name":"LinkedGroupId","value":""}}]}]}]}]}